moki_panda/__init__.py
moki_panda/envs/__init__.py
moki_panda/envs/panda_env.py
moki_panda-0.0.2.dist-info/METADATA
moki_panda-0.0.2.dist-info/WHEEL
moki_panda-0.0.2.dist-info/top_level.txt
moki_panda-0.0.2.dist-info/RECORD
